worderrorrate/__init__.py
worderrorrate/version.py
worderrorrate-0.1.2.dist-info/LICENSE
worderrorrate-0.1.2.dist-info/METADATA
worderrorrate-0.1.2.dist-info/WHEEL
worderrorrate-0.1.2.dist-info/top_level.txt
worderrorrate-0.1.2.dist-info/RECORD
