Metadata-Version: 2.1
Name: worderrorrate
Version: 0.1.2
Summary: Alignment and word error rate calculations
Author: David A. van Leeuwen
Author-email: "David A. van Leeuwen" <david.vanleeuwen@gmail.com>
License: MIT License
Project-URL: Homepage, https://github.com/davidavdav/WordErrorRate.py
Project-URL: Bug Tracker, https://github.com/davidavdav/WordErrorRate.py/issues
Classifier: Programming Language :: Python :: 3
Classifier: License :: OSI Approved :: MIT License
Classifier: Operating System :: OS Independent
Requires-Python: >=3.7
License-File: LICENSE
Requires-Dist: numpy
